<ruleset xmlns="http://codenarc.org/ruleset/1.0" xmlns:xsi="http://www.w3.org/2001/XMLSchema-instance"
         xsi:schemaLocation="http://codenarc.org/ruleset/1.0 http://codenarc.org/ruleset-schema.xsd"
         xsi:noNamespaceSchemaLocation="http://codenarc.org/ruleset-schema.xsd">
  <ruleset-ref path="rulesets/basic.xml"/>
  <ruleset-ref path="rulesets/braces.xml"/>
  <ruleset-ref path="rulesets/imports.xml">
    <rule-config name="MisorderedStaticImports">
      <property name="comesBefore" value="false"/>
    </rule-config>
  </ruleset-ref>
  <ruleset-ref path="rulesets/naming.xml">
    <rule-config name="ClassName">
      <property name="regex" value="^[A-Z][\$a-zA-Z0-9]*$"/>
    </rule-config>
    <rule-config name="FactoryMethodName">
      <property name="regex" value="(build.*)"/>
    </rule-config>
    <rule-config name="FieldName">
      <property name="finalRegex" value="^[a-z][a-zA-Z0-9]*$"/>
      <property name="staticFinalRegex" value="^logger$|^[A-Z][A-Z_0-9]*$|^serialVersionUID$"/>
    </rule-config>
    <rule-config name="MethodName">
      <property name="regex" value="^[a-z][\$_a-zA-Z0-9]*$|^.*\s.*$"/>
    </rule-config>
    <rule-config name="VariableName">
      <property name="finalRegex" value="^[a-z][a-zA-Z0-9]*$"/>
    </rule-config>
  </ruleset-ref>
</ruleset>
